CreLanguageTranslate/LanguageTranslate.py
CreLanguageTranslate/TranslateBase.py
CreLanguageTranslate/__init__.py
CreLanguageTranslate/googleTranslate.py
CreLanguageTranslate/translateInstance.py
crelanguagetranslate-0.0.23.dist-info/METADATA
crelanguagetranslate-0.0.23.dist-info/WHEEL
crelanguagetranslate-0.0.23.dist-info/licenses/LICENSE
crelanguagetranslate-0.0.23.dist-info/RECORD
