Metadata-Version: 2.3
Name: CreLanguageTranslate
Version: 0.0.23
Summary: A Translator Adapter
Project-URL: Homepage, https://github.com/SnakeOilBottles/CreLanguageTranslate
Project-URL: Issues, https://github.com/SnakeOilBottles/CreLanguageTranslate/issues
Author-email: Michael Kahle <michael.kahle@yahoo.de>
License:                                  Apache License
License-File: LICENSE
Classifier: License :: OSI Approved :: Apache Software License
Classifier: Operating System :: OS Independent
Classifier: Programming Language :: Python :: 3
Requires-Python: >=3.8
Requires-Dist: deep-translator
